neuromynerva/__init__.py
neuromynerva/_version.py
neuromynerva/labextension/package.json
neuromynerva/labextension/schemas/@flybrainlab/neuromynerva/package.json.orig
neuromynerva/labextension/schemas/@flybrainlab/neuromynerva/plugin.json
neuromynerva/labextension/schemas/@flybrainlab/neuromynerva/plugin.json.local
neuromynerva/labextension/static/100.1eea715bf0ac5398d8f5.js
neuromynerva/labextension/static/132.6a8d446cf96d19c2c3b3.js
neuromynerva/labextension/static/132.6a8d446cf96d19c2c3b3.js.LICENSE.txt
neuromynerva/labextension/static/204.cfa360407c87109cace8.js
neuromynerva/labextension/static/204.cfa360407c87109cace8.js.LICENSE.txt
neuromynerva/labextension/static/212.1d763db78d74c5fdb841.js
neuromynerva/labextension/static/212.1d763db78d74c5fdb841.js.LICENSE.txt
neuromynerva/labextension/static/232.7552bbc1bec9f8af5cd7.js
neuromynerva/labextension/static/402.c82a2a6fb08fb4b49843.js
neuromynerva/labextension/static/402.c82a2a6fb08fb4b49843.js.LICENSE.txt
neuromynerva/labextension/static/405.53dd1aae43bbd5edc8b1.js
neuromynerva/labextension/static/722.35ccbbc2ae2a88369b0a.js
neuromynerva/labextension/static/722.35ccbbc2ae2a88369b0a.js.LICENSE.txt
neuromynerva/labextension/static/776.762a272a1bae65d6d25c.js
neuromynerva/labextension/static/911.5afb6e583df7aeb93ff7.js
neuromynerva/labextension/static/915.c7ad8626dd6b2b0fec3a.js
neuromynerva/labextension/static/remoteEntry.0ff86a7e30e584be1d26.js
neuromynerva/labextension/static/style.js
neuromynerva/labextension/static/third-party-licenses.json
neuromynerva-0.2.17.data/data/share/jupyter/labextensions/@flybrainlab/neuromynerva/install.json
neuromynerva-0.2.17.data/data/share/jupyter/labextensions/@flybrainlab/neuromynerva/package.json
neuromynerva-0.2.17.data/data/share/jupyter/labextensions/@flybrainlab/neuromynerva/schemas/@flybrainlab/neuromynerva/package.json.orig
neuromynerva-0.2.17.data/data/share/jupyter/labextensions/@flybrainlab/neuromynerva/schemas/@flybrainlab/neuromynerva/plugin.json
neuromynerva-0.2.17.dist-info/LICENSE
neuromynerva-0.2.17.dist-info/METADATA
neuromynerva-0.2.17.dist-info/WHEEL
neuromynerva-0.2.17.dist-info/top_level.txt
neuromynerva-0.2.17.dist-info/RECORD
