Metadata-Version: 2.1
Name: neuromynerva
Version: 0.2.17
Summary: NeuroMynerva extension for FlyBrainLab
Home-page: https://github.com/FlyBrainLab/NeuroMynerva/
Author: FlyBrainLab Dev Team
Author-email: tl2747@columbia.edu
License: BSD-3-Clause
Keywords: FlyBrainLab,Drosophila,fruit fly,JupyterLab,JupyterLab3
Platform: Linux
Platform: Mac OS X
Platform: Windows
Classifier: License :: OSI Approved :: BSD License
Classifier: Programming Language :: Python
Classifier: Programming Language :: Python :: 3
Classifier: Programming Language :: Python :: 3.7
Classifier: Programming Language :: Python :: 3.8
Classifier: Programming Language :: Python :: 3.9
Classifier: Programming Language :: Python :: 3.10
Classifier: Framework :: Jupyter
Requires-Python: >=3.7
License-File: LICENSE
Requires-Dist: jupyterlab (~=3.0)
Requires-Dist: jupyter-packaging
